{
  "info": {
    "key": "g768_0417"
  },
  "sheets": {
    "מזומנים": {
      "columns": [
        "שם נ\"ע",
        "מספר ני\"ע",
        "מספר מנפיק",
        "דירוג",
        "שם מדרג",
        "סוג מטבע",
        "שיעור ריבית",
        "תשואה לפידיון",
        "שווי שוק",
        "שיעור מנכסי אפיק ה השקעה",
        "שעור מנכסי השקעה"
      ],
      "data": [
        [
          "מזומן (מזרחי)",
          4,
          20,
          "AAA IL",
          "S&P מעלות",
          "שקל חדש",
          "",
          "",
          28306.86,
          0.5869,
          0.1014
        ],
        [
          "מעבר הון עמיתים ס.ש (מזרחי)",
          419257001,
          20,
          "AAA IL",
          "S&P מעלות",
          "שקל חדש",
          "",
          "",
          461.99,
          0.0096,
          0.0017
        ],
        [
          "דולר אמריקאי (מזרחי)",
          14,
          20,
          "AAA IL",
          "S&P מעלות",
          "דולר אמריקאי",
          "",
          "",
          332.89,
          0.0069,
          0.0012
        ],
        [
          "מזומן אירו (מזרחי)",
          1010,
          20,
          "AAA IL",
          "S&P מעלות",
          "אירו",
          "",
          "",
          377.78,
          0.0078,
          0.0014
        ],
        [
          "מזומן יין יפני (הבינלאומי)",
          1002,
          31,
          "AA+ IL",
          "S&P מעלות",
          "יין יפני",
          "",
          "",
          1.6,
          0.0,
          0.0
        ],
        [
          "מזומן מקסיקו פזו (מזרחי)",
          1021,
          20,
          "AAA IL",
          "S&P מעלות",
          "מקסיקו פזו",
          "",
          "",
          0.79,
          0.0,
          0.0
        ],
        [
          "HSBC USD (HSBC)",
          "HSBC USD",
          "",
          "AA-",
          "Fitch",
          "דולר אמריקאי",
          "",
          "",
          14320.66,
          0.2969,
          0.0513
        ]
      ]
    },
    "תעודות התחייבות ממשלתיות": {
      "columns": [
        "שם נ\"ע",
        "מספר ני\"ע",
        "זירת מסחר",
        "דירוג",
        "שם מדרג",
        "תאריך רכישה",
        "מח\"מ",
        "סוג מטבע",
        "שיעור ריבית",
        "תשואה לפידיון",
        "ערך נקוב",
        "שער",
        "פידיון/ריבית לקבל",
        "שווי שוק",
        "שעור מערך נקוב מונפק",
        "שיעור מנכסי אפיק ההשקעה",
        "שעור מנכסי השקעה"
      ],
      "data": [
        [
          "גליל 5903",
          9590332,
          "TASE",
          "RF",
          "",
          "",
          3.38,
          "שקל חדש",
          0.04,
          -0.0046,
          10659859,
          152.55,
          0.0,
          16261.61,
          0.0007,
          0.0706,
          0.0583
        ],
        [
          "גליל 5904",
          9590431,
          "TASE",
          "RF",
          "",
          "",
          5.94,
          "שקל חדש",
          0.04,
          -0.0014,
          194634,
          158.14,
          0.0,
          307.79,
          0.0,
          0.0013,
          0.0011
        ],
        [
          "ממצמ0418",
          1108927,
          "TASE",
          "RF",
          "",
          "",
          0.33,
          "שקל חדש",
          0.035,
          0.0098,
          2496983,
          120.2,
          0.0,
          3001.37,
          0.0002,
          0.013,
          0.0108
        ],
        [
          "ממשל צמודה 0545",
          1134865,
          "TASE",
          "RF",
          "",
          "",
          23.78,
          "שקל חדש",
          0.01,
          0.014,
          1332675,
          91.55,
          0.0,
          1220.06,
          0.0002,
          0.0053,
          0.0044
        ],
        [
          "ממשל צמודה 0841",
          1120583,
          "TASE",
          "RF",
          "",
          "",
          18.48,
          "שקל חדש",
          0.0275,
          0.0118,
          712393,
          141.55,
          0.0,
          1008.39,
          0.0,
          0.0044,
          0.0036
        ],
        [
          "ממשל צמודה 1019",
          1114750,
          "TASE",
          "RF",
          "",
          "",
          1.81,
          "שקל חדש",
          0.03,
          -0.0049,
          332936,
          116.8,
          0.0,
          388.87,
          0.0,
          0.0017,
          0.0014
        ],
        [
          "ממשל צמודה 1020",
          1137181,
          "TASE",
          "RF",
          "",
          "",
          2.84,
          "שקל חדש",
          0.001,
          -0.0049,
          12432240,
          101.73,
          0.0,
          12647.32,
          0.0009,
          0.0549,
          0.0453
        ],
        [
          "ממשל צמודה 1025",
          1135912,
          "TASE",
          "RF",
          "",
          "",
          7.65,
          "שקל חדש",
          0.0075,
          0.0002,
          6678,
          105.47,
          0.0,
          7.04,
          0.0,
          0.0,
          0.0
        ],
        [
          "ממשלתי צמוד 0536",
          1097708,
          "TASE",
          "RF",
          "",
          "",
          14.25,
          "שקל חדש",
          0.04,
          0.0088,
          160686,
          183.07,
          0.0,
          294.17,
          0.0,
          0.0013,
          0.0011
        ],
        [
          "ממשלתי צמוד 0922",
          1124056,
          "TASE",
          "RF",
          "",
          "",
          4.52,
          "שקל חדש",
          0.0275,
          -0.0041,
          5939945,
          119.08,
          0.0,
          7073.29,
          0.0004,
          0.0307,
          0.0253
        ],
        [
          "ממשלתי צמוד 0923",
          1128081,
          "TASE",
          "RF",
          "",
          "",
          5.52,
          "שקל חדש",
          0.0175,
          -0.0026,
          4495,
          113.12,
          0.0,
          5.08,
          0.0,
          0.0,
          0.0
        ],
        [
          "מ.ק.מ 118",
          8180119,
          "TASE",
          "RF",
          "",
          "",
          0.02,
          "שקל חדש",
          "",
          0.0061,
          47000,
          100.0,
          0.0,
          47.0,
          0.0,
          0.0002,
          0.0002
        ],
        [
          "מ.ק.מ 318",
          8180317,
          "TASE",
          "RF",
          "",
          "",
          0.19,
          "שקל חדש",
          "",
          0.0016,
          627853,
          99.98,
          0.0,
          627.73,
          0.0001,
          0.0027,
          0.0022
        ],
        [
          "מ.ק.מ 618",
          8180614,
          "TASE",
          "RF",
          "",
          "",
          0.44,
          "שקל חדש",
          "",
          0.0009,
          22269347,
          99.96,
          0.0,
          22260.44,
          0.0032,
          0.0966,
          0.0797
        ],
        [
          "מ.ק.מ 718",
          8180713,
          "TASE",
          "RF",
          "",
          "",
          0.52,
          "שקל חדש",
          "",
          0.0014,
          7790117,
          99.96,
          0.0,
          7787.0,
          0.0011,
          0.0338,
          0.0279
        ],
        [
          "מ.ק.מ 828",
          8180820,
          "TASE",
          "RF",
          "",
          "",
          0.61,
          "שקל חדש",
          "",
          0.0011,
          5742993,
          99.93,
          0.0,
          5738.97,
          0.0008,
          0.0249,
          0.0206
        ],
        [
          "מ.ק.מ 918",
          8180911,
          "TASE",
          "RF",
          "",
          "",
          0.69,
          "שקל חדש",
          "",
          0.0013,
          8837474,
          99.92,
          0.0,
          8830.4,
          0.0013,
          0.0383,
          0.0316
        ],
        [
          "מק\"מ 1018",
          8181018,
          "TASE",
          "RF",
          "",
          "",
          0.76,
          "שקל חדש",
          "",
          0.0013,
          4630167,
          99.93,
          0.0,
          4626.93,
          0.0007,
          0.0201,
          0.0166
        ],
        [
          "מק\"מ 1118",
          8181117,
          "TASE",
          "RF",
          "",
          "",
          0.86,
          "שקל חדש",
          "",
          0.0012,
          22952501,
          99.9,
          0.0,
          22929.55,
          0.0029,
          0.0995,
          0.0821
        ],
        [
          "מק\"מ 1218",
          8181216,
          "TASE",
          "RF",
          "",
          "",
          0.94,
          "שקל חדש",
          "",
          0.0011,
          16593209,
          99.89,
          0.0,
          16574.96,
          0.0021,
          0.072,
          0.0594
        ],
        [
          "מק\"מ 218",
          8180218,
          "TASE",
          "RF",
          "",
          "",
          0.11,
          "שקל חדש",
          "",
          0.0018,
          10363,
          99.98,
          0.0,
          10.36,
          0.0,
          0.0,
          0.0
        ],
        [
          "מק\"מ 428",
          8180424,
          "TASE",
          "RF",
          "",
          "",
          0.28,
          "שקל חדש",
          "",
          0.0014,
          200000,
          99.97,
          0.0,
          199.94,
          0.0,
          0.0009,
          0.0007
        ],
        [
          "מק\"מ 518",
          8180515,
          "TASE",
          "RF",
          "",
          "",
          0.34,
          "שקל חדש",
          "",
          0.0012,
          9521489,
          99.96,
          0.0,
          9517.68,
          0.0014,
          0.0413,
          0.0341
        ],
        [
          "ממשל שקלית 0120",
          1115773,
          "TASE",
          "RF",
          "",
          "",
          1.96,
          "שקל חדש",
          0.05,
          0.0019,
          5808729,
          114.6,
          0.0,
          6656.8,
          0.0003,
          0.0289,
          0.0238
        ],
        [
          "ממשל שקלית 0121",
          1142223,
          "TASE",
          "RF",
          "",
          "",
          3.08,
          "שקל חדש",
          0.005,
          0.0035,
          974656,
          100.56,
          0.0,
          980.11,
          0.0006,
          0.0043,
          0.0035
        ],
        [
          "ממשל שקלית 0122",
          1123272,
          "TASE",
          "RF",
          "",
          "",
          3.66,
          "שקל חדש",
          0.055,
          0.0051,
          685067,
          125.16,
          0.0,
          857.43,
          0.0,
          0.0037,
          0.0031
        ],
        [
          "ממשל שקלית 0142",
          1125400,
          "TASE",
          "RF",
          "",
          "",
          15.28,
          "שקל חדש",
          0.055,
          0.0272,
          11117426,
          153.97,
          0.0,
          17117.5,
          0.0006,
          0.0743,
          0.0613
        ],
        [
          "ממשל שקלית 0323",
          1126747,
          "TASE",
          "RF",
          "",
          "",
          4.73,
          "שקל חדש",
          0.0425,
          0.0078,
          306298,
          121.01,
          0.0,
          370.65,
          0.0,
          0.0016,
          0.0013
        ],
        [
          "ממשל שקלית 0327",
          1139344,
          "TASE",
          "RF",
          "",
          "",
          8.44,
          "שקל חדש",
          0.02,
          0.0164,
          12175688,
          104.77,
          0.0,
          12756.47,
          0.0011,
          0.0554,
          0.0457
        ],
        [
          "ממשל שקלית 0421",
          1138130,
          "TASE",
          "RF",
          "",
          "",
          3.28,
          "שקל חדש",
          0.01,
          0.0039,
          6741491,
          102.7,
          0.0,
          6923.51,
          0.0005,
          0.0301,
          0.0248
        ],
        [
          "ממשל שקלית 0519",
          1131770,
          "TASE",
          "RF",
          "",
          "",
          1.4,
          "שקל חדש",
          0.0225,
          0.0012,
          7167023,
          104.34,
          0.0,
          7478.07,
          0.0004,
          0.0325,
          0.0268
        ],
        [
          "ממשלתי שקלי 0118",
          1126218,
          "TASE",
          "RF",
          "",
          "",
          0.09,
          "שקל חדש",
          0.04,
          0.0021,
          724555,
          103.99,
          0.0,
          753.46,
          0.0001,
          0.0033,
          0.0027
        ],
        [
          "ממשלתי שקלי 0324",
          1130848,
          "TASE",
          "RF",
          "",
          "",
          5.61,
          "שקל חדש",
          0.0375,
          0.0103,
          98900,
          119.31,
          0.0,
          118.0,
          0.0,
          0.0005,
          0.0004
        ],
        [
          "ממשלתי שקלי 0347",
          1140193,
          "TASE",
          "RF",
          "",
          "",
          18.59,
          "שקל חדש",
          0.0375,
          0.0299,
          858883,
          117.83,
          0.0,
          1012.02,
          0.0003,
          0.0044,
          0.0036
        ],
        [
          "ממשלתי שקלי 0825",
          1135557,
          "TASE",
          "RF",
          "",
          "",
          7.22,
          "שקל חדש",
          0.0175,
          0.0137,
          5241,
          103.49,
          0.0,
          5.42,
          0.0,
          0.0,
          0.0
        ],
        [
          "ממשלתי שקלי 1026",
          1099456,
          "TASE",
          "RF",
          "",
          "",
          7.31,
          "שקל חדש",
          0.0625,
          0.0147,
          30420,
          140.56,
          0.0,
          42.76,
          0.0,
          0.0002,
          0.0002
        ],
        [
          "ממשק 0219 6%",
          1110907,
          "TASE",
          "RF",
          "",
          "",
          1.11,
          "שקל חדש",
          0.06,
          0.0013,
          4400650,
          111.85,
          0.0,
          4922.13,
          0.0002,
          0.0214,
          0.0176
        ],
        [
          "ממשל משתנה 1121",
          1127646,
          "TASE",
          "RF",
          "",
          "",
          3.92,
          "שקל חדש",
          0.0011,
          0.0018,
          21476504,
          99.75,
          0.0,
          21422.81,
          0.0015,
          0.093,
          0.0767
        ],
        [
          "ממשלתי ריבית משתנה 0",
          1116193,
          "TASE",
          "RF",
          "",
          "",
          2.42,
          "שקל חדש",
          0.0011,
          0.0015,
          7023006,
          99.94,
          0.0,
          7018.79,
          0.0004,
          0.0305,
          0.0251
        ],
        [
          "ISRAE 3.1 06/23",
          "US4651387M19",
          "אחר",
          "A+",
          "S&P",
          "",
          5.09,
          "דולר אמריקאי",
          0.0315,
          0.0271,
          105000,
          103.94,
          5.73,
          378.37,
          0.0001,
          0.0016,
          0.0014
        ],
        [
          "T 1.75 10/31/18",
          "US912828RP73",
          "FWB",
          "AA+",
          "S&P",
          "",
          0.83,
          "דולר אמריקאי",
          0.0175,
          0.0176,
          45000,
          100.29,
          0.0,
          156.47,
          0.0,
          0.0007,
          0.0006
        ]
      ]
    },
    "אופציות": {
      "columns": [
        "שם נ\"ע",
        "מספר ני\"ע",
        "זירת מסחר",
        "ענף מסחר",
        "סוג מטבע",
        "ערך נקוב",
        "שער",
        "שווי שוק",
        "שעור מערך נקוב מונפק",
        "שיעור מנכסי אפיק ההשקעה",
        "שעור מנכסי השקעה"
      ],
      "data": [
        [
          "C 1510 JAN",
          82174962,
          "TASE",
          "ל.ר.",
          "שקל חדש",
          274,
          160800,
          440.59,
          "",
          88.7217,
          0.0016
        ],
        [
          "P 1510 JAN",
          82175530,
          "TASE",
          "ל.ר.",
          "שקל חדש",
          -274,
          155900,
          -427.17,
          "",
          -86.0181,
          -0.0015
        ],
        [
          "C 355.0 FEB$",
          82195231,
          "TASE",
          "ל.ר.",
          "שקל חדש",
          48,
          9800,
          4.7,
          "",
          0.9472,
          0.0
        ],
        [
          "C 365.0 FEB$",
          82195249,
          "TASE",
          "ל.ר.",
          "שקל חדש",
          -72,
          6600,
          -4.75,
          "",
          -0.9569,
          0.0
        ],
        [
          "P 345.0 FEB$",
          82195348,
          "TASE",
          "ל.ר.",
          "שקל חדש",
          -12,
          24000,
          -2.88,
          "",
          -0.5799,
          0.0
        ],
        [
          "P 350.0 FEB$",
          82195272,
          "TASE",
          "ל.ר.",
          "שקל חדש",
          -12,
          46100,
          -5.53,
          "",
          -1.114,
          0.0
        ]
      ]
    },
    "חוזים עתידיים": {
      "columns": [
        "שם נ\"ע",
        "מספר ני\"ע",
        "זירת מסחר",
        "ענף מסחר",
        "סוג מטבע",
        "ערך נקוב",
        "שער",
        "שווי שוק",
        "שיעור מנכסי אפיק ההשקעה",
        "שעור מנכסי השקעה"
      ],
      "data": [
        [
          "F  NIKKEI225",
          "NXH8",
          "אחר",
          "ל.ר.",
          "דולר אמריקאי",
          24,
          2274000.0,
          97.77,
          0.198,
          0.0004
        ],
        [
          "F 03/18 EUROSTOX",
          "VGH8",
          "אחר",
          "ל.ר.",
          "אירו",
          55,
          349300.0,
          -196.42,
          -0.3978,
          -0.0007
        ],
        [
          "F 03/18 FTSE",
          "Z H8",
          "אחר",
          "ל.ר.",
          "לירה שטרלינג",
          6,
          763800.0,
          58.57,
          0.1186,
          0.0002
        ],
        [
          "F 03/18 MINI DAX",
          "DFWH8",
          "אחר",
          "ל.ר.",
          "אירו",
          5,
          1291000.0,
          -23.46,
          -0.0475,
          -0.0001
        ],
        [
          "F 03/18 MINI NSDQ",
          "NQH8",
          "אחר",
          "ל.ר.",
          "דולר אמריקאי",
          6,
          640875.0,
          -3.2,
          -0.0065,
          0.0
        ],
        [
          "F 03/18 MSCI",
          "MESH8",
          "אחר",
          "ל.ר.",
          "דולר אמריקאי",
          46,
          116370.0,
          418.32,
          0.8472,
          0.0015
        ],
        [
          "F 3/18 10YRTR",
          "TYH8",
          "אחר",
          "ל.ר.",
          "דולר אמריקאי",
          -3,
          12404.69,
          7.15,
          0.0145,
          0.0
        ],
        [
          "F3/18 EURO BU",
          "RXH8",
          "אחר",
          "ל.ר.",
          "אירו",
          -4,
          16168.0,
          20.44,
          0.0414,
          0.0001
        ],
        [
          "F3/18 MINI S&P500",
          "ESH7",
          "אחר",
          "ל.ר.",
          "דולר אמריקאי",
          57,
          267600.0,
          114.62,
          0.2321,
          0.0004
        ]
      ]
    },
    "לא סחיר - חוזים עתידיים": {
      "columns": [
        "שם נ\"ע",
        "מספר ני\"ע",
        "ענף מסחר",
        "תאריך רכישה",
        "סוג מטבע",
        "ערך נקוב",
        "שער",
        "שווי הוגן",
        "שיעור מנכסי אפיק ההשקעה",
        "שעור מנכסי השקעה"
      ],
      "data": [
        [
          "FW USD/ILS 24/01/18 3.504 סיטי",
          777103268,
          "ל.ר.",
          "",
          "שקל חדש",
          -168440.0,
          -3.64,
          6.14,
          0.7849,
          0.0
        ],
        [
          "FW080218 USD/NIS3.48",
          426107827,
          "ל.ר.",
          "4/12/2017",
          "שקל חדש",
          865000.0,
          -2.33,
          -20.18,
          -2.5796,
          -0.0001
        ],
        [
          "FW170118 USD/NIS3.49",
          425196771,
          "ל.ר.",
          "16/10/2017",
          "שקל חדש",
          2983000.0,
          -2.12,
          -63.25,
          -8.0861,
          -0.0002
        ],
        [
          "FW210218 USD/NIS3.48",
          426117925,
          "ל.ר.",
          "4/12/2017",
          "שקל חדש",
          -88500.0,
          -1.97,
          1.75,
          0.2234,
          0.0
        ],
        [
          "FW210218 USD/NIS3.54",
          425770443,
          "ל.ר.",
          "14/11/2017",
          "שקל חדש",
          -279000.0,
          -7.62,
          21.27,
          2.7191,
          0.0001
        ],
        [
          "FW250418 USD/NIS3.47",
          425348224,
          "ל.ר.",
          "23/10/2017",
          "שקל חדש",
          -2464200.0,
          -1.74,
          42.94,
          5.4898,
          0.0002
        ],
        [
          "FW070218 USD/JPY113.",
          426228847,
          "ל.ר.",
          "8/12/2017",
          "יין יפני",
          46894.35,
          -67.94,
          -0.98,
          -0.1255,
          0.0
        ],
        [
          "FW140218 GBP/USD1.31",
          425735206,
          "ל.ר.",
          "13/11/2017",
          "דולר אמריקאי",
          31000.0,
          3.94,
          4.24,
          0.5419,
          0.0
        ],
        [
          "FW170118 EUR/USD1.18",
          425347242,
          "ל.ר.",
          "23/10/2017",
          "דולר אמריקאי",
          52000.0,
          1.91,
          3.45,
          0.4408,
          0.0
        ],
        [
          "FW170118 EUR/USD1.19",
          425795366,
          "ל.ר.",
          "15/11/2017",
          "דולר אמריקאי",
          350000.0,
          1.03,
          12.45,
          1.5913,
          0.0
        ]
      ]
    },
    "השקעות אחרות": {
      "columns": [
        "שם נ\"ע",
        "מספר ני\"ע",
        "דירוג",
        "שם מדרג",
        "סוג מטבע",
        "שיעור ריבית",
        "תשואה לפידיון",
        "שווי הוגן",
        "שיעור מנכסי אפיק ה השקעה",
        "שעור מנכסי השקעה"
      ],
      "data": [
        [
          "חוז עמיתים - דס\"ש",
          530030,
          "NR IL",
          "",
          "שקל חדש",
          "",
          "",
          90.31,
          1.0014,
          0.0003
        ],
        [
          "מעבר פקדונות",
          419256003,
          "NR IL",
          "",
          "שקל חדש",
          "",
          "",
          -0.12,
          -0.0014,
          0.0
        ]
      ]
    }
  }
}