{
  "info": {
    "key": "g7981_0417"
  },
  "sheets": {
    "מזומנים": {
      "columns": [
        "שם נ\"ע",
        "מספר ני\"ע",
        "מספר מנפיק",
        "דירוג",
        "שם מדרג",
        "סוג מטבע",
        "שיעור ריבית",
        "תשואה לפידיון",
        "שווי שוק",
        "שיעור מנכסי אפיק ה השקעה",
        "שעור מנכסי השקעה"
      ],
      "data": [
        [
          "מזומן (מזרחי)",
          4,
          20,
          "AAA IL",
          "S&P מעלות",
          "שקל חדש",
          "",
          "",
          1025.75,
          0.826,
          0.1248
        ],
        [
          "מעבר הון עמיתים ס.ש (מזרחי)",
          419257001,
          20,
          "AAA IL",
          "S&P מעלות",
          "שקל חדש",
          "",
          "",
          210.0,
          0.1691,
          0.0256
        ],
        [
          "דולר אמריקאי (מזרחי)",
          14,
          20,
          "AAA IL",
          "S&P מעלות",
          "דולר אמריקאי",
          "",
          "",
          8.12,
          0.0065,
          0.001
        ],
        [
          "מזומן אירו (מזרחי)",
          1010,
          20,
          "AAA IL",
          "S&P מעלות",
          "אירו",
          "",
          "",
          -2.0,
          -0.0016,
          -0.0002
        ],
        [
          "מזומן יין יפני (הבינלאומי)",
          1002,
          31,
          "AA+ IL",
          "S&P מעלות",
          "יין יפני",
          "",
          "",
          0.03,
          0.0,
          0.0
        ]
      ]
    },
    "תעודות התחייבות ממשלתיות": {
      "columns": [
        "שם נ\"ע",
        "מספר ני\"ע",
        "זירת מסחר",
        "דירוג",
        "שם מדרג",
        "תאריך רכישה",
        "מח\"מ",
        "סוג מטבע",
        "שיעור ריבית",
        "תשואה לפידיון",
        "ערך נקוב",
        "שער",
        "פידיון/ריבית לקבל",
        "שווי שוק",
        "שעור מערך נקוב מונפק",
        "שיעור מנכסי אפיק ההשקעה",
        "שעור מנכסי השקעה"
      ],
      "data": [
        [
          "גליל 5903",
          9590332,
          "TASE",
          "RF",
          "",
          "",
          3.38,
          "שקל חדש",
          0.04,
          -0.0046,
          161460,
          152.55,
          0,
          246.31,
          0,
          0.0822,
          0.03
        ],
        [
          "גליל 5904",
          9590431,
          "TASE",
          "RF",
          "",
          "",
          5.94,
          "שקל חדש",
          0.04,
          -0.0014,
          81300,
          158.14,
          0,
          128.57,
          0,
          0.0429,
          0.0156
        ],
        [
          "ממצמ0418",
          1108927,
          "TASE",
          "RF",
          "",
          "",
          0.33,
          "שקל חדש",
          0.035,
          0.0098,
          65064,
          120.2,
          0,
          78.21,
          0,
          0.0261,
          0.0095
        ],
        [
          "ממשל צמודה 0841",
          1120583,
          "TASE",
          "RF",
          "",
          "",
          18.48,
          "שקל חדש",
          0.0275,
          0.0118,
          22000,
          141.55,
          0,
          31.14,
          0,
          0.0104,
          0.0038
        ],
        [
          "ממשל צמודה 1020",
          1137181,
          "TASE",
          "RF",
          "",
          "",
          2.84,
          "שקל חדש",
          0.001,
          -0.0049,
          73954,
          101.73,
          0,
          75.23,
          0,
          0.0251,
          0.0092
        ],
        [
          "ממשל צמודה 1025",
          1135912,
          "TASE",
          "RF",
          "",
          "",
          7.65,
          "שקל חדש",
          0.0075,
          0.0002,
          30000,
          105.47,
          0,
          31.64,
          0,
          0.0106,
          0.0039
        ],
        [
          "ממשלתי צמוד 0922",
          1124056,
          "TASE",
          "RF",
          "",
          "",
          4.52,
          "שקל חדש",
          0.0275,
          -0.0041,
          210338,
          119.08,
          0,
          250.47,
          0,
          0.0836,
          0.0305
        ],
        [
          "מ.ק.מ 618",
          8180614,
          "TASE",
          "RF",
          "",
          "",
          0.44,
          "שקל חדש",
          "",
          0.0009,
          90000,
          99.96,
          0,
          89.96,
          0,
          0.03,
          0.0109
        ],
        [
          "מ.ק.מ 718",
          8180713,
          "TASE",
          "RF",
          "",
          "",
          0.52,
          "שקל חדש",
          "",
          0.0014,
          52000,
          99.96,
          0,
          51.98,
          0,
          0.0173,
          0.0063
        ],
        [
          "מ.ק.מ 828",
          8180820,
          "TASE",
          "RF",
          "",
          "",
          0.61,
          "שקל חדש",
          "",
          0.0011,
          70000,
          99.93,
          0,
          69.95,
          0,
          0.0233,
          0.0085
        ],
        [
          "מ.ק.מ 918",
          8180911,
          "TASE",
          "RF",
          "",
          "",
          0.69,
          "שקל חדש",
          "",
          0.0013,
          240000,
          99.92,
          0,
          239.81,
          0,
          0.08,
          0.0292
        ],
        [
          "מק\"מ 1218",
          8181216,
          "TASE",
          "RF",
          "",
          "",
          0.94,
          "שקל חדש",
          "",
          0.0011,
          6009,
          99.89,
          0,
          6.0,
          0,
          0.002,
          0.0007
        ],
        [
          "מק\"מ 218",
          8180218,
          "TASE",
          "RF",
          "",
          "",
          0.11,
          "שקל חדש",
          "",
          0.0018,
          18000,
          99.98,
          0,
          18.0,
          0,
          0.006,
          0.0022
        ],
        [
          "מק\"מ 428",
          8180424,
          "TASE",
          "RF",
          "",
          "",
          0.28,
          "שקל חדש",
          "",
          0.0014,
          180000,
          99.97,
          0,
          179.95,
          0,
          0.06,
          0.0219
        ],
        [
          "ממשל שקלית 0122",
          1123272,
          "TASE",
          "RF",
          "",
          "",
          3.66,
          "שקל חדש",
          0.055,
          0.0051,
          73673,
          125.16,
          0,
          92.21,
          0,
          0.0308,
          0.0112
        ],
        [
          "ממשל שקלית 0142",
          1125400,
          "TASE",
          "RF",
          "",
          "",
          15.28,
          "שקל חדש",
          0.055,
          0.0272,
          195400,
          153.97,
          0,
          300.86,
          0,
          0.1004,
          0.0366
        ],
        [
          "ממשל שקלית 0323",
          1126747,
          "TASE",
          "RF",
          "",
          "",
          4.73,
          "שקל חדש",
          0.0425,
          0.0078,
          142729,
          121.01,
          0,
          172.72,
          0,
          0.0576,
          0.021
        ],
        [
          "ממשל שקלית 0327",
          1139344,
          "TASE",
          "RF",
          "",
          "",
          8.44,
          "שקל חדש",
          0.02,
          0.0164,
          254500,
          104.77,
          0,
          266.64,
          0,
          0.089,
          0.0325
        ],
        [
          "ממשל שקלית 0421",
          1138130,
          "TASE",
          "RF",
          "",
          "",
          3.28,
          "שקל חדש",
          0.01,
          0.0039,
          61847,
          102.7,
          0,
          63.52,
          0,
          0.0212,
          0.0077
        ],
        [
          "ממשלתי שקלי 0324",
          1130848,
          "TASE",
          "RF",
          "",
          "",
          5.61,
          "שקל חדש",
          0.0375,
          0.0103,
          110680,
          119.31,
          0,
          132.05,
          0,
          0.0441,
          0.0161
        ],
        [
          "ממשל משתנה 1121",
          1127646,
          "TASE",
          "RF",
          "",
          "",
          3.92,
          "שקל חדש",
          0.0011,
          0.0018,
          442000,
          99.75,
          0,
          440.89,
          0,
          0.1471,
          0.0537
        ],
        [
          "ממשלתי ריבית משתנה 0",
          1116193,
          "TASE",
          "RF",
          "",
          "",
          2.42,
          "שקל חדש",
          0.0011,
          0.0015,
          31139,
          99.94,
          0,
          31.12,
          0,
          0.0104,
          0.0038
        ]
      ]
    },
    "אג\"ח קונצרני": {
      "columns": [
        "שם נ\"ע",
        "מספר ני\"ע",
        "זירת מסחר",
        "ספק מידע",
        "מספר מנפיק",
        "ענף מסחר",
        "דירוג",
        "שם מדרג",
        "תאריך רכישה",
        "מח\"מ",
        "סוג מטבע",
        "שיעור ריבית",
        "תשואה לפידיון",
        "ערך נקוב",
        "שער",
        "פידיון/ריבית לקבל",
        "שווי שוק",
        "שעור מערך נקוב מונפק",
        "שיעור מנכסי אפיק ההשקעה",
        "שעור מנכסי השקעה"
      ],
      "data": [
        [
          "חברה לישראל 7",
          5760160,
          "TASE",
          "",
          520028010,
          "השקעה ואחזקות",
          "A IL",
          "S&P מעלות",
          "",
          1.65,
          "שקל חדש",
          0.0495,
          0.0085,
          12882,
          130.12,
          0,
          16.76,
          0,
          0.2433,
          0.002
        ],
        [
          "אפריקה אגח כז",
          6110431,
          "TASE",
          "",
          520005067,
          "נדל\"ן ובינוי",
          "NR IL",
          "",
          "",
          7.38,
          "שקל חדש",
          0.068,
          0.0298,
          18242,
          81.2,
          0,
          14.81,
          0,
          0.215,
          0.0018
        ],
        [
          "אפרק.ק26",
          6110365,
          "TASE",
          "",
          520005067,
          "נדל\"ן ובינוי",
          "NR IL",
          "",
          "",
          7.38,
          "שקל חדש",
          0.075,
          0.0301,
          16789,
          87.02,
          0,
          14.61,
          0,
          0.2121,
          0.0018
        ],
        [
          "דיסק השק  אגח י",
          6390348,
          "TASE",
          "",
          520023896,
          "השקעה ואחזקות",
          "BBB IL",
          "S&P מעלות",
          "",
          5.66,
          "שקל חדש",
          0.048,
          0.0399,
          21193,
          105.09,
          0,
          22.27,
          0,
          0.3233,
          0.0027
        ],
        [
          "רציו מימון אגח ג",
          1142488,
          "TASE",
          "",
          515060044,
          "חיפושי נפט וגז",
          "NR IL",
          "",
          "",
          4.29,
          "שקל חדש",
          0.03,
          0.0647,
          432,
          101.78,
          0,
          0.44,
          0,
          0.0064,
          0.0001
        ]
      ]
    },
    "תעודות סל": {
      "columns": [
        "שם נ\"ע",
        "מספר ני\"ע",
        "זירת מסחר",
        "מספר מנפיק",
        "ענף מסחר",
        "סוג מטבע",
        "ערך נקוב",
        "שער",
        "פידיון/ריבית לקבל",
        "שווי שוק",
        "שעור מערך נקוב מונפק",
        "שיעור מנכסי אפיק ההשקעה",
        "שעור מנכסי השקעה"
      ],
      "data": [
        [
          "תכלית תא 100 (*) (*)",
          1091818,
          "TASE",
          513594101,
          "מדדי מניות בארץ",
          "שקל חדש",
          2332,
          13550.0,
          0.0,
          315.99,
          0.0001,
          0.0844,
          0.0385
        ],
        [
          "הראל סל תל בונד 60",
          1113257,
          "TASE",
          514103811,
          "מדדים אחרים בארץ",
          "שקל חדש",
          184139,
          324.99,
          0.0,
          598.43,
          0.0007,
          0.1599,
          0.0728
        ],
        [
          "מבטמדד מט בנד60",
          1109479,
          "TASE",
          513665661,
          "מדדים אחרים בארץ",
          "שקל חדש",
          217938,
          326.29,
          0.0,
          711.11,
          0.0005,
          0.19,
          0.0865
        ],
        [
          "קסםסמ סד בונד60",
          1109248,
          "TASE",
          513502211,
          "מדדים אחרים בארץ",
          "שקל חדש",
          21930,
          3243.07,
          0.0,
          711.21,
          0.0002,
          0.19,
          0.0866
        ],
        [
          "תכלמר טו בונד60 (*) (*)",
          1109362,
          "TASE",
          513944660,
          "מדדים אחרים בארץ",
          "שקל חדש",
          16079,
          3258.5,
          0.0,
          523.93,
          0.0001,
          0.14,
          0.0638
        ],
        [
          "LYXOR ETF MSCI",
          "FR0011079466",
          "CAC",
          "",
          "מדדי מניות בחול",
          "אירו",
          404,
          23149.0,
          0.0,
          388.36,
          0.0005,
          0.1037,
          0.0473
        ],
        [
          "ISHARES MARKIT",
          "IE00B4PY7Y77",
          "LSE",
          "",
          "מדדים אחרים בחול",
          "דולר אמריקאי",
          604,
          10372.0,
          0.0,
          217.2,
          0.0,
          0.058,
          0.0264
        ],
        [
          "ISHARES USD COR",
          "IE0032895942",
          "LSE",
          "",
          "מדדים אחרים בחול",
          "דולר אמריקאי",
          427,
          11671.0,
          1.44,
          174.22,
          0.0,
          0.0465,
          0.0212
        ],
        [
          "SPDR EMERGING M",
          "IE00B4613386",
          "LSE",
          "",
          "מדדים אחרים בחול",
          "דולר אמריקאי",
          392,
          7588.0,
          0.0,
          103.13,
          0.0,
          0.0275,
          0.0126
        ]
      ]
    },
    "קרנות נאמנות": {
      "columns": [
        "שם נ\"ע",
        "מספר ני\"ע",
        "זירת מסחר",
        "מספר מנפיק",
        "ענף מסחר",
        "דירוג",
        "שם מדרג",
        "סוג מטבע",
        "ערך נקוב",
        "שער",
        "שווי שוק",
        "שעור מערך נקוב מונפק",
        "שיעור מנכסי אפיק ההשקעה",
        "שעור מנכסי השקעה"
      ],
      "data": [
        [
          "POWERSHARES SEN",
          "US73936Q7694",
          "NYSE",
          "",
          "אג\"ח קונצרני",
          "NR",
          "",
          "דולר אמריקאי",
          2003,
          2304,
          160,
          0,
          1,
          0.0195
        ]
      ]
    },
    "לא סחיר - חוזים עתידיים": {
      "columns": [
        "שם נ\"ע",
        "מספר ני\"ע",
        "ענף מסחר",
        "תאריך רכישה",
        "סוג מטבע",
        "ערך נקוב",
        "שער",
        "שווי הוגן",
        "שיעור מנכסי אפיק ההשקעה",
        "שעור מנכסי השקעה"
      ],
      "data": [
        [
          "FW080218 USD/NIS3.48",
          426109922,
          "ל.ר.",
          "4/12/2017",
          "שקל חדש",
          -16113.0,
          -2.33,
          0.38,
          0.0799,
          0.0
        ],
        [
          "FW170118 USD/NIS3.49",
          425196482,
          "ל.ר.",
          "16/10/2017",
          "שקל חדש",
          -1000.0,
          -2.12,
          0.02,
          0.0045,
          0.0
        ],
        [
          "FW170118 USD/NIS3.52",
          425896875,
          "ל.ר.",
          "21/11/2017",
          "שקל חדש",
          -5000.0,
          -5.32,
          0.27,
          0.0565,
          0.0
        ],
        [
          "FW210218 USD/NIS3.48",
          426117818,
          "ל.ר.",
          "4/12/2017",
          "שקל חדש",
          -4000.0,
          -1.97,
          0.08,
          0.0168,
          0.0
        ],
        [
          "FW210218 USD/NIS3.54",
          425770419,
          "ל.ר.",
          "14/11/2017",
          "שקל חדש",
          -25500.0,
          -7.62,
          1.94,
          0.4131,
          0.0002
        ],
        [
          "FW240118 USD/NIS3.50",
          425869096,
          "ל.ר.",
          "20/11/2017",
          "שקל חדש",
          -1000.0,
          -4.02,
          0.04,
          0.0085,
          0.0
        ],
        [
          "FW250418 USD/NIS3.47",
          425348356,
          "ל.ר.",
          "23/10/2017",
          "שקל חדש",
          -32000.0,
          -1.74,
          0.56,
          0.1185,
          0.0001
        ],
        [
          "FW070218 USD/JPY113.",
          426228805,
          "ל.ר.",
          "8/12/2017",
          "יין יפני",
          884.8,
          -67.81,
          -0.02,
          -0.0039,
          0.0
        ],
        [
          "FW170118 EUR/USD1.18",
          425347291,
          "ל.ר.",
          "23/10/2017",
          "דולר אמריקאי",
          11000.0,
          1.91,
          0.73,
          0.155,
          0.0001
        ],
        [
          "FW170118 EUR/USD1.19",
          425795259,
          "ל.ר.",
          "15/11/2017",
          "דולר אמריקאי",
          20000.0,
          1.03,
          0.71,
          0.1511,
          0.0001
        ]
      ]
    }
  }
}