{
  "info": {
    "key": "g8704_0417"
  },
  "sheets": {
    "מזומנים": {
      "columns": [
        "שם המנפיק/שם נייר ערך",
        "מספר ני\"ע",
        "מספר מנפיק",
        "דירוג",
        "שם מדרג",
        "סוג מטבע",
        "שיעור ריבית",
        "תשואה לפידיון",
        "שווי שוק",
        "שעור מנכסי אפיק ההשקעה",
        "שעור מסך נכסי השקעה"
      ],
      "data": [
        [
          "לאומי 29984033",
          301,
          10,
          "",
          "",
          "שקל חדש",
          0,
          0,
          0.85,
          100,
          0.17
        ]
      ]
    },
    "תעודות סל": {
      "columns": [
        "שם המנפיק/שם נייר ערך",
        "מספר ני\"ע",
        "זירת מסחר",
        "מספר מנפיק",
        "ענף מסחר",
        "סוג מטבע",
        "ערך נקוב",
        "שער",
        "פדיון/ריבית לקבל ",
        "שווי שוק",
        "שעור מערך נקוב מונפק",
        "שעור מנכסי אפיק ההשקעה",
        "שעור מסך נכסי השקעה"
      ],
      "data": [
        [
          "הראל סל תל בונד 20",
          1113240,
          "TASE",
          1523,
          "אג״ח",
          "שקל חדש",
          37629,
          336.71,
          0,
          126.7,
          0.02,
          25.0,
          24.96
        ],
        [
          "פסגות סל בונד 20",
          1104603,
          "TASE",
          1446,
          "אג״ח",
          "שקל חדש",
          37992,
          333.49,
          0,
          126.7,
          0.01,
          25.0,
          24.96
        ],
        [
          "קסם תל בונד 20",
          1101633,
          "TASE",
          1224,
          "אג״ח",
          "שקל חדש",
          3792,
          3339.83,
          0,
          126.65,
          0.0,
          24.99,
          24.95
        ],
        [
          "תכלית תל בונד 20",
          1102276,
          "TASE",
          1336,
          "אג״ח",
          "שקל חדש",
          75563,
          167.65,
          0,
          126.68,
          0.01,
          25.0,
          24.96
        ]
      ]
    }
  }
}